[
  {
    "id": "ka_aa",
    "consonant_id": "ka",
    "vowel_id": "aa",
    "devanagari": "का",
    "roman": "kā",
    "mahabharata_count": 23868
  },
  {
    "id": "ka_i",
    "consonant_id": "ka",
    "vowel_id": "i",
    "devanagari": "कि",
    "roman": "ki",
    "mahabharata_count": 6692
  },
  {
    "id": "ka_ii",
    "consonant_id": "ka",
    "vowel_id": "ii",
    "devanagari": "की",
    "roman": "kī",
    "mahabharata_count": 2691
  },
  {
    "id": "ka_u",
    "consonant_id": "ka",
    "vowel_id": "u",
    "devanagari": "कु",
    "roman": "ku",
    "mahabharata_count": 12276
  },
  {
    "id": "ka_uu",
    "consonant_id": "ka",
    "vowel_id": "uu",
    "devanagari": "कू",
    "roman": "kū",
    "mahabharata_count": 628
  },
  {
    "id": "ka_RRi",
    "consonant_id": "ka",
    "vowel_id": "RRi",
    "devanagari": "कृ",
    "roman": "kṛ",
    "mahabharata_count": 15471
  },
  {
    "id": "ka_LLi",
    "consonant_id": "ka",
    "vowel_id": "LLi",
    "devanagari": "कॢ",
    "roman": "kḷ",
    "mahabharata_count": 33
  },
  {
    "id": "ka_e",
    "consonant_id": "ka",
    "vowel_id": "e",
    "devanagari": "के",
    "roman": "ke",
    "mahabharata_count": 7369
  },
  {
    "id": "ka_ai",
    "consonant_id": "ka",
    "vowel_id": "ai",
    "devanagari": "कै",
    "roman": "kai",
    "mahabharata_count": 1315
  },
  {
    "id": "ka_o",
    "consonant_id": "ka",
    "vowel_id": "o",
    "devanagari": "को",
    "roman": "ko",
    "mahabharata_count": 3727
  },
  {
    "id": "ka_au",
    "consonant_id": "ka",
    "vowel_id": "au",
    "devanagari": "कौ",
    "roman": "kau",
    "mahabharata_count": 2566
  },
  {
    "id": "ka_aM",
    "consonant_id": "ka",
    "vowel_id": "aM",
    "devanagari": "कं",
    "roman": "kaṁ",
    "mahabharata_count": 3327
  },
  {
    "id": "ka_aH",
    "consonant_id": "ka",
    "vowel_id": "aH",
    "devanagari": "कः",
    "roman": "kaḥ",
    "mahabharata_count": 2001
  },
  {
    "id": "kha_aa",
    "consonant_id": "kha",
    "vowel_id": "aa",
    "devanagari": "खा",
    "roman": "khā",
    "mahabharata_count": 2214
  },
  {
    "id": "kha_i",
    "consonant_id": "kha",
    "vowel_id": "i",
    "devanagari": "खि",
    "roman": "khi",
    "mahabharata_count": 754
  },
  {
    "id": "kha_ii",
    "consonant_id": "kha",
    "vowel_id": "ii",
    "devanagari": "खी",
    "roman": "khī",
    "mahabharata_count": 286
  },
  {
    "id": "kha_u",
    "consonant_id": "kha",
    "vowel_id": "u",
    "devanagari": "खु",
    "roman": "khu",
    "mahabharata_count": 59
  },
  {
    "id": "kha_e",
    "consonant_id": "kha",
    "vowel_id": "e",
    "devanagari": "खे",
    "roman": "khe",
    "mahabharata_count": 745
  },
  {
    "id": "kha_ai",
    "consonant_id": "kha",
    "vowel_id": "ai",
    "devanagari": "खै",
    "roman": "khai",
    "mahabharata_count": 379
  },
  {
    "id": "kha_o",
    "consonant_id": "kha",
    "vowel_id": "o",
    "devanagari": "खो",
    "roman": "kho",
    "mahabharata_count": 331
  },
  {
    "id": "kha_au",
    "consonant_id": "kha",
    "vowel_id": "au",
    "devanagari": "खौ",
    "roman": "khau",
    "mahabharata_count": 23
  },
  {
    "id": "kha_aM",
    "consonant_id": "kha",
    "vowel_id": "aM",
    "devanagari": "खं",
    "roman": "khaṁ",
    "mahabharata_count": 1112
  },
  {
    "id": "kha_aH",
    "consonant_id": "kha",
    "vowel_id": "aH",
    "devanagari": "खः",
    "roman": "khaḥ",
    "mahabharata_count": 257
  },
  {
    "id": "ga_aa",
    "consonant_id": "ga",
    "vowel_id": "aa",
    "devanagari": "गा",
    "roman": "gā",
    "mahabharata_count": 8878
  },
  {
    "id": "ga_i",
    "consonant_id": "ga",
    "vowel_id": "i",
    "devanagari": "गि",
    "roman": "gi",
    "mahabharata_count": 1662
  },
  {
    "id": "ga_ii",
    "consonant_id": "ga",
    "vowel_id": "ii",
    "devanagari": "गी",
    "roman": "gī",
    "mahabharata_count": 1012
  },
  {
    "id": "ga_u",
    "consonant_id": "ga",
    "vowel_id": "u",
    "devanagari": "गु",
    "roman": "gu",
    "mahabharata_count": 5272
  },
  {
    "id": "ga_uu",
    "consonant_id": "ga",
    "vowel_id": "uu",
    "devanagari": "गू",
    "roman": "gū",
    "mahabharata_count": 253
  },
  {
    "id": "ga_RRi",
    "consonant_id": "ga",
    "vowel_id": "RRi",
    "devanagari": "गृ",
    "roman": "gṛ",
    "mahabharata_count": 3152
  },
  {
    "id": "ga_e",
    "consonant_id": "ga",
    "vowel_id": "e",
    "devanagari": "गे",
    "roman": "ge",
    "mahabharata_count": 2965
  },
  {
    "id": "ga_ai",
    "consonant_id": "ga",
    "vowel_id": "ai",
    "devanagari": "गै",
    "roman": "gai",
    "mahabharata_count": 743
  },
  {
    "id": "ga_o",
    "consonant_id": "ga",
    "vowel_id": "o",
    "devanagari": "गो",
    "roman": "go",
    "mahabharata_count": 2806
  },
  {
    "id": "ga_au",
    "consonant_id": "ga",
    "vowel_id": "au",
    "devanagari": "गौ",
    "roman": "gau",
    "mahabharata_count": 651
  },
  {
    "id": "ga_aM",
    "consonant_id": "ga",
    "vowel_id": "aM",
    "devanagari": "गं",
    "roman": "gaṁ",
    "mahabharata_count": 1456
  },
  {
    "id": "ga_aH",
    "consonant_id": "ga",
    "vowel_id": "aH",
    "devanagari": "गः",
    "roman": "gaḥ",
    "mahabharata_count": 725
  },
  {
    "id": "gha_aa",
    "consonant_id": "gha",
    "vowel_id": "aa",
    "devanagari": "घा",
    "roman": "ghā",
    "mahabharata_count": 2053
  },
  {
    "id": "gha_i",
    "consonant_id": "gha",
    "vowel_id": "i",
    "devanagari": "घि",
    "roman": "ghi",
    "mahabharata_count": 38
  },
  {
    "id": "gha_ii",
    "consonant_id": "gha",
    "vowel_id": "ii",
    "devanagari": "घी",
    "roman": "ghī",
    "mahabharata_count": 44
  },
  {
    "id": "gha_u",
    "consonant_id": "gha",
    "vowel_id": "u",
    "devanagari": "घु",
    "roman": "ghu",
    "mahabharata_count": 199
  },
  {
    "id": "gha_uu",
    "consonant_id": "gha",
    "vowel_id": "uu",
    "devanagari": "घू",
    "roman": "ghū",
    "mahabharata_count": 49
  },
  {
    "id": "gha_RRi",
    "consonant_id": "gha",
    "vowel_id": "RRi",
    "devanagari": "घृ",
    "roman": "ghṛ",
    "mahabharata_count": 258
  },
  {
    "id": "gha_e",
    "consonant_id": "gha",
    "vowel_id": "e",
    "devanagari": "घे",
    "roman": "ghe",
    "mahabharata_count": 137
  },
  {
    "id": "gha_ai",
    "consonant_id": "gha",
    "vowel_id": "ai",
    "devanagari": "घै",
    "roman": "ghai",
    "mahabharata_count": 249
  },
  {
    "id": "gha_o",
    "consonant_id": "gha",
    "vowel_id": "o",
    "devanagari": "घो",
    "roman": "gho",
    "mahabharata_count": 1987
  },
  {
    "id": "gha_au",
    "consonant_id": "gha",
    "vowel_id": "au",
    "devanagari": "घौ",
    "roman": "ghau",
    "mahabharata_count": 21
  },
  {
    "id": "gha_aM",
    "consonant_id": "gha",
    "vowel_id": "aM",
    "devanagari": "घं",
    "roman": "ghaṁ",
    "mahabharata_count": 137
  },
  {
    "id": "gha_aH",
    "consonant_id": "gha",
    "vowel_id": "aH",
    "devanagari": "घः",
    "roman": "ghaḥ",
    "mahabharata_count": 56
  },
  {
    "id": "ca_aa",
    "consonant_id": "ca",
    "vowel_id": "aa",
    "devanagari": "चा",
    "roman": "cā",
    "mahabharata_count": 15529
  },
  {
    "id": "ca_i",
    "consonant_id": "ca",
    "vowel_id": "i",
    "devanagari": "चि",
    "roman": "ci",
    "mahabharata_count": 11370
  },
  {
    "id": "ca_ii",
    "consonant_id": "ca",
    "vowel_id": "ii",
    "devanagari": "ची",
    "roman": "cī",
    "mahabharata_count": 635
  },
  {
    "id": "ca_u",
    "consonant_id": "ca",
    "vowel_id": "u",
    "devanagari": "चु",
    "roman": "cu",
    "mahabharata_count": 671
  },
  {
    "id": "ca_uu",
    "consonant_id": "ca",
    "vowel_id": "uu",
    "devanagari": "चू",
    "roman": "cū",
    "mahabharata_count": 144
  },
  {
    "id": "ca_RRi",
    "consonant_id": "ca",
    "vowel_id": "RRi",
    "devanagari": "चृ",
    "roman": "cṛ",
    "mahabharata_count": 2
  },
  {
    "id": "ca_e",
    "consonant_id": "ca",
    "vowel_id": "e",
    "devanagari": "चे",
    "roman": "ce",
    "mahabharata_count": 3297
  },
  {
    "id": "ca_ai",
    "consonant_id": "ca",
    "vowel_id": "ai",
    "devanagari": "चै",
    "roman": "cai",
    "mahabharata_count": 7413
  },
  {
    "id": "ca_o",
    "consonant_id": "ca",
    "vowel_id": "o",
    "devanagari": "चो",
    "roman": "co",
    "mahabharata_count": 2144
  },
  {
    "id": "ca_au",
    "consonant_id": "ca",
    "vowel_id": "au",
    "devanagari": "चौ",
    "roman": "cau",
    "mahabharata_count": 107
  },
  {
    "id": "ca_aM",
    "consonant_id": "ca",
    "vowel_id": "aM",
    "devanagari": "चं",
    "roman": "caṁ",
    "mahabharata_count": 412
  },
  {
    "id": "ca_aH",
    "consonant_id": "ca",
    "vowel_id": "aH",
    "devanagari": "चः",
    "roman": "caḥ",
    "mahabharata_count": 1014
  },
  {
    "id": "cha_aa",
    "consonant_id": "cha",
    "vowel_id": "aa",
    "devanagari": "छा",
    "roman": "chā",
    "mahabharata_count": 1839
  },
  {
    "id": "cha_i",
    "consonant_id": "cha",
    "vowel_id": "i",
    "devanagari": "छि",
    "roman": "chi",
    "mahabharata_count": 1321
  },
  {
    "id": "cha_ii",
    "consonant_id": "cha",
    "vowel_id": "ii",
    "devanagari": "छी",
    "roman": "chī",
    "mahabharata_count": 63
  },
  {
    "id": "cha_u",
    "consonant_id": "cha",
    "vowel_id": "u",
    "devanagari": "छु",
    "roman": "chu",
    "mahabharata_count": 165
  },
  {
    "id": "cha_uu",
    "consonant_id": "cha",
    "vowel_id": "uu",
    "devanagari": "छू",
    "roman": "chū",
    "mahabharata_count": 71
  },
  {
    "id": "cha_RRi",
    "consonant_id": "cha",
    "vowel_id": "RRi",
    "devanagari": "छृ",
    "roman": "chṛ",
    "mahabharata_count": 124
  },
  {
    "id": "cha_e",
    "consonant_id": "cha",
    "vowel_id": "e",
    "devanagari": "छे",
    "roman": "che",
    "mahabharata_count": 1422
  },
  {
    "id": "cha_ai",
    "consonant_id": "cha",
    "vowel_id": "ai",
    "devanagari": "छै",
    "roman": "chai",
    "mahabharata_count": 40
  },
  {
    "id": "cha_o",
    "consonant_id": "cha",
    "vowel_id": "o",
    "devanagari": "छो",
    "roman": "cho",
    "mahabharata_count": 93
  },
  {
    "id": "cha_au",
    "consonant_id": "cha",
    "vowel_id": "au",
    "devanagari": "छौ",
    "roman": "chau",
    "mahabharata_count": 14
  },
  {
    "id": "cha_aM",
    "consonant_id": "cha",
    "vowel_id": "aM",
    "devanagari": "छं",
    "roman": "chaṁ",
    "mahabharata_count": 77
  },
  {
    "id": "cha_aH",
    "consonant_id": "cha",
    "vowel_id": "aH",
    "devanagari": "छः",
    "roman": "chaḥ",
    "mahabharata_count": 3
  },
  {
    "id": "ja_aa",
    "consonant_id": "ja",
    "vowel_id": "aa",
    "devanagari": "जा",
    "roman": "jā",
    "mahabharata_count": 13878
  },
  {
    "id": "ja_i",
    "consonant_id": "ja",
    "vowel_id": "i",
    "devanagari": "जि",
    "roman": "ji",
    "mahabharata_count": 5199
  },
  {
    "id": "ja_ii",
    "consonant_id": "ja",
    "vowel_id": "ii",
    "devanagari": "जी",
    "roman": "jī",
    "mahabharata_count": 2473
  },
  {
    "id": "ja_u",
    "consonant_id": "ja",
    "vowel_id": "u",
    "devanagari": "जु",
    "roman": "ju",
    "mahabharata_count": 2689
  },
  {
    "id": "ja_uu",
    "consonant_id": "ja",
    "vowel_id": "uu",
    "devanagari": "जू",
    "roman": "jū",
    "mahabharata_count": 44
  },
  {
    "id": "ja_RRi",
    "consonant_id": "ja",
    "vowel_id": "RRi",
    "devanagari": "जृ",
    "roman": "jṛ",
    "mahabharata_count": 38
  },
  {
    "id": "ja_e",
    "consonant_id": "ja",
    "vowel_id": "e",
    "devanagari": "जे",
    "roman": "je",
    "mahabharata_count": 2741
  },
  {
    "id": "ja_ai",
    "consonant_id": "ja",
    "vowel_id": "ai",
    "devanagari": "जै",
    "roman": "jai",
    "mahabharata_count": 469
  },
  {
    "id": "ja_o",
    "consonant_id": "ja",
    "vowel_id": "o",
    "devanagari": "जो",
    "roman": "jo",
    "mahabharata_count": 1738
  },
  {
    "id": "ja_au",
    "consonant_id": "ja",
    "vowel_id": "au",
    "devanagari": "जौ",
    "roman": "jau",
    "mahabharata_count": 328
  },
  {
    "id": "ja_aM",
    "consonant_id": "ja",
    "vowel_id": "aM",
    "devanagari": "जं",
    "roman": "jaṁ",
    "mahabharata_count": 1581
  },
  {
    "id": "ja_aH",
    "consonant_id": "ja",
    "vowel_id": "aH",
    "devanagari": "जः",
    "roman": "jaḥ",
    "mahabharata_count": 1316
  },
  {
    "id": "jha_i",
    "consonant_id": "jha",
    "vowel_id": "i",
    "devanagari": "झि",
    "roman": "jhi",
    "mahabharata_count": 12
  },
  {
    "id": "jha_o",
    "consonant_id": "jha",
    "vowel_id": "o",
    "devanagari": "झो",
    "roman": "jho",
    "mahabharata_count": 1
  },
  {
    "id": "JNa_aa",
    "consonant_id": "JNa",
    "vowel_id": "aa",
    "devanagari": "ञा",
    "roman": "ñā",
    "mahabharata_count": 4
  },
  {
    "id": "Ta_aa",
    "consonant_id": "Ta",
    "vowel_id": "aa",
    "devanagari": "टा",
    "roman": "ṭā",
    "mahabharata_count": 3070
  },
  {
    "id": "Ta_i",
    "consonant_id": "Ta",
    "vowel_id": "i",
    "devanagari": "टि",
    "roman": "ṭi",
    "mahabharata_count": 1616
  },
  {
    "id": "Ta_ii",
    "consonant_id": "Ta",
    "vowel_id": "ii",
    "devanagari": "टी",
    "roman": "ṭī",
    "mahabharata_count": 245
  },
  {
    "id": "Ta_u",
    "consonant_id": "Ta",
    "vowel_id": "u",
    "devanagari": "टु",
    "roman": "ṭu",
    "mahabharata_count": 683
  },
  {
    "id": "Ta_uu",
    "consonant_id": "Ta",
    "vowel_id": "uu",
    "devanagari": "टू",
    "roman": "ṭū",
    "mahabharata_count": 3
  },
  {
    "id": "Ta_RRi",
    "consonant_id": "Ta",
    "vowel_id": "RRi",
    "devanagari": "टृ",
    "roman": "ṭṛ",
    "mahabharata_count": 3
  },
  {
    "id": "Ta_RRI",
    "consonant_id": "Ta",
    "vowel_id": "RRI",
    "devanagari": "टॄ",
    "roman": "ṭṝ",
    "mahabharata_count": 1
  },
  {
    "id": "Ta_e",
    "consonant_id": "Ta",
    "vowel_id": "e",
    "devanagari": "टे",
    "roman": "ṭe",
    "mahabharata_count": 672
  },
  {
    "id": "Ta_ai",
    "consonant_id": "Ta",
    "vowel_id": "ai",
    "devanagari": "टै",
    "roman": "ṭai",
    "mahabharata_count": 195
  },
  {
    "id": "Ta_o",
    "consonant_id": "Ta",
    "vowel_id": "o",
    "devanagari": "टो",
    "roman": "ṭo",
    "mahabharata_count": 1157
  },
  {
    "id": "Ta_au",
    "consonant_id": "Ta",
    "vowel_id": "au",
    "devanagari": "टौ",
    "roman": "ṭau",
    "mahabharata_count": 264
  },
  {
    "id": "Ta_aM",
    "consonant_id": "Ta",
    "vowel_id": "aM",
    "devanagari": "टं",
    "roman": "ṭaṁ",
    "mahabharata_count": 1110
  },
  {
    "id": "Ta_aH",
    "consonant_id": "Ta",
    "vowel_id": "aH",
    "devanagari": "टः",
    "roman": "ṭaḥ",
    "mahabharata_count": 668
  },
  {
    "id": "Tha_aa",
    "consonant_id": "Tha",
    "vowel_id": "aa",
    "devanagari": "ठा",
    "roman": "ṭhā",
    "mahabharata_count": 1122
  },
  {
    "id": "Tha_i",
    "consonant_id": "Tha",
    "vowel_id": "i",
    "devanagari": "ठि",
    "roman": "ṭhi",
    "mahabharata_count": 3578
  },
  {
    "id": "Tha_ii",
    "consonant_id": "Tha",
    "vowel_id": "ii",
    "devanagari": "ठी",
    "roman": "ṭhī",
    "mahabharata_count": 75
  },
  {
    "id": "Tha_u",
    "consonant_id": "Tha",
    "vowel_id": "u",
    "devanagari": "ठु",
    "roman": "ṭhu",
    "mahabharata_count": 35
  },
  {
    "id": "Tha_uu",
    "consonant_id": "Tha",
    "vowel_id": "uu",
    "devanagari": "ठू",
    "roman": "ṭhū",
    "mahabharata_count": 3
  },
  {
    "id": "Tha_e",
    "consonant_id": "Tha",
    "vowel_id": "e",
    "devanagari": "ठे",
    "roman": "ṭhe",
    "mahabharata_count": 633
  },
  {
    "id": "Tha_ai",
    "consonant_id": "Tha",
    "vowel_id": "ai",
    "devanagari": "ठै",
    "roman": "ṭhai",
    "mahabharata_count": 60
  },
  {
    "id": "Tha_o",
    "consonant_id": "Tha",
    "vowel_id": "o",
    "devanagari": "ठो",
    "roman": "ṭho",
    "mahabharata_count": 450
  },
  {
    "id": "Tha_au",
    "consonant_id": "Tha",
    "vowel_id": "au",
    "devanagari": "ठौ",
    "roman": "ṭhau",
    "mahabharata_count": 31
  },
  {
    "id": "Tha_aM",
    "consonant_id": "Tha",
    "vowel_id": "aM",
    "devanagari": "ठं",
    "roman": "ṭhaṁ",
    "mahabharata_count": 636
  },
  {
    "id": "Tha_aH",
    "consonant_id": "Tha",
    "vowel_id": "aH",
    "devanagari": "ठः",
    "roman": "ṭhaḥ",
    "mahabharata_count": 339
  },
  {
    "id": "Da_aa",
    "consonant_id": "Da",
    "vowel_id": "aa",
    "devanagari": "डा",
    "roman": "ḍā",
    "mahabharata_count": 807
  },
  {
    "id": "Da_i",
    "consonant_id": "Da",
    "vowel_id": "i",
    "devanagari": "डि",
    "roman": "ḍi",
    "mahabharata_count": 1464
  },
  {
    "id": "Da_ii",
    "consonant_id": "Da",
    "vowel_id": "ii",
    "devanagari": "डी",
    "roman": "ḍī",
    "mahabharata_count": 650
  },
  {
    "id": "Da_u",
    "consonant_id": "Da",
    "vowel_id": "u",
    "devanagari": "डु",
    "roman": "ḍu",
    "mahabharata_count": 1040
  },
  {
    "id": "Da_uu",
    "consonant_id": "Da",
    "vowel_id": "uu",
    "devanagari": "डू",
    "roman": "ḍū",
    "mahabharata_count": 235
  },
  {
    "id": "Da_RRi",
    "consonant_id": "Da",
    "vowel_id": "RRi",
    "devanagari": "डृ",
    "roman": "ḍṛ",
    "mahabharata_count": 1
  },
  {
    "id": "Da_e",
    "consonant_id": "Da",
    "vowel_id": "e",
    "devanagari": "डे",
    "roman": "ḍe",
    "mahabharata_count": 467
  },
  {
    "id": "Da_ai",
    "consonant_id": "Da",
    "vowel_id": "ai",
    "devanagari": "डै",
    "roman": "ḍai",
    "mahabharata_count": 60
  },
  {
    "id": "Da_o",
    "consonant_id": "Da",
    "vowel_id": "o",
    "devanagari": "डो",
    "roman": "ḍo",
    "mahabharata_count": 309
  },
  {
    "id": "Da_au",
    "consonant_id": "Da",
    "vowel_id": "au",
    "devanagari": "डौ",
    "roman": "ḍau",
    "mahabharata_count": 11
  },
  {
    "id": "Da_aM",
    "consonant_id": "Da",
    "vowel_id": "aM",
    "devanagari": "डं",
    "roman": "ḍaṁ",
    "mahabharata_count": 173
  },
  {
    "id": "Da_aH",
    "consonant_id": "Da",
    "vowel_id": "aH",
    "devanagari": "डः",
    "roman": "ḍaḥ",
    "mahabharata_count": 116
  },
  {
    "id": "Dha_aa",
    "consonant_id": "Dha",
    "vowel_id": "aa",
    "devanagari": "ढा",
    "roman": "ḍhā",
    "mahabharata_count": 330
  },
  {
    "id": "Dha_ii",
    "consonant_id": "Dha",
    "vowel_id": "ii",
    "devanagari": "ढी",
    "roman": "ḍhī",
    "mahabharata_count": 7
  },
  {
    "id": "Dha_u",
    "consonant_id": "Dha",
    "vowel_id": "u",
    "devanagari": "ढु",
    "roman": "ḍhu",
    "mahabharata_count": 94
  },
  {
    "id": "Dha_e",
    "consonant_id": "Dha",
    "vowel_id": "e",
    "devanagari": "ढे",
    "roman": "ḍhe",
    "mahabharata_count": 89
  },
  {
    "id": "Dha_ai",
    "consonant_id": "Dha",
    "vowel_id": "ai",
    "devanagari": "ढै",
    "roman": "ḍhai",
    "mahabharata_count": 28
  },
  {
    "id": "Dha_o",
    "consonant_id": "Dha",
    "vowel_id": "o",
    "devanagari": "ढो",
    "roman": "ḍho",
    "mahabharata_count": 132
  },
  {
    "id": "Dha_au",
    "consonant_id": "Dha",
    "vowel_id": "au",
    "devanagari": "ढौ",
    "roman": "ḍhau",
    "mahabharata_count": 11
  },
  {
    "id": "Dha_aM",
    "consonant_id": "Dha",
    "vowel_id": "aM",
    "devanagari": "ढं",
    "roman": "ḍhaṁ",
    "mahabharata_count": 173
  },
  {
    "id": "Dha_aH",
    "consonant_id": "Dha",
    "vowel_id": "aH",
    "devanagari": "ढः",
    "roman": "ḍhaḥ",
    "mahabharata_count": 71
  },
  {
    "id": "Na_aa",
    "consonant_id": "Na",
    "vowel_id": "aa",
    "devanagari": "णा",
    "roman": "ṇā",
    "mahabharata_count": 17088
  },
  {
    "id": "Na_i",
    "consonant_id": "Na",
    "vowel_id": "i",
    "devanagari": "णि",
    "roman": "ṇi",
    "mahabharata_count": 7266
  },
  {
    "id": "Na_ii",
    "consonant_id": "Na",
    "vowel_id": "ii",
    "devanagari": "णी",
    "roman": "ṇī",
    "mahabharata_count": 2228
  },
  {
    "id": "Na_u",
    "consonant_id": "Na",
    "vowel_id": "u",
    "devanagari": "णु",
    "roman": "ṇu",
    "mahabharata_count": 2154
  },
  {
    "id": "Na_uu",
    "consonant_id": "Na",
    "vowel_id": "uu",
    "devanagari": "णू",
    "roman": "ṇū",
    "mahabharata_count": 41
  },
  {
    "id": "Na_e",
    "consonant_id": "Na",
    "vowel_id": "e",
    "devanagari": "णे",
    "roman": "ṇe",
    "mahabharata_count": 5738
  },
  {
    "id": "Na_ai",
    "consonant_id": "Na",
    "vowel_id": "ai",
    "devanagari": "णै",
    "roman": "ṇai",
    "mahabharata_count": 2290
  },
  {
    "id": "Na_o",
    "consonant_id": "Na",
    "vowel_id": "o",
    "devanagari": "णो",
    "roman": "ṇo",
    "mahabharata_count": 3432
  },
  {
    "id": "Na_au",
    "consonant_id": "Na",
    "vowel_id": "au",
    "devanagari": "णौ",
    "roman": "ṇau",
    "mahabharata_count": 581
  },
  {
    "id": "Na_aM",
    "consonant_id": "Na",
    "vowel_id": "aM",
    "devanagari": "णं",
    "roman": "ṇaṁ",
    "mahabharata_count": 5250
  },
  {
    "id": "Na_aH",
    "consonant_id": "Na",
    "vowel_id": "aH",
    "devanagari": "णः",
    "roman": "ṇaḥ",
    "mahabharata_count": 3429
  },
  {
    "id": "ta_aa",
    "consonant_id": "ta",
    "vowel_id": "aa",
    "devanagari": "ता",
    "roman": "tā",
    "mahabharata_count": 55813
  },
  {
    "id": "ta_i",
    "consonant_id": "ta",
    "vowel_id": "i",
    "devanagari": "ति",
    "roman": "ti",
    "mahabharata_count": 48680
  },
  {
    "id": "ta_ii",
    "consonant_id": "ta",
    "vowel_id": "ii",
    "devanagari": "ती",
    "roman": "tī",
    "mahabharata_count": 7939
  },
  {
    "id": "ta_u",
    "consonant_id": "ta",
    "vowel_id": "u",
    "devanagari": "तु",
    "roman": "tu",
    "mahabharata_count": 23771
  },
  {
    "id": "ta_uu",
    "consonant_id": "ta",
    "vowel_id": "uu",
    "devanagari": "तू",
    "roman": "tū",
    "mahabharata_count": 1301
  },
  {
    "id": "ta_RRi",
    "consonant_id": "ta",
    "vowel_id": "RRi",
    "devanagari": "तृ",
    "roman": "tṛ",
    "mahabharata_count": 2228
  },
  {
    "id": "ta_RRI",
    "consonant_id": "ta",
    "vowel_id": "RRI",
    "devanagari": "तॄ",
    "roman": "tṝ",
    "mahabharata_count": 663
  },
  {
    "id": "ta_e",
    "consonant_id": "ta",
    "vowel_id": "e",
    "devanagari": "ते",
    "roman": "te",
    "mahabharata_count": 44038
  },
  {
    "id": "ta_ai",
    "consonant_id": "ta",
    "vowel_id": "ai",
    "devanagari": "तै",
    "roman": "tai",
    "mahabharata_count": 4290
  },
  {
    "id": "ta_o",
    "consonant_id": "ta",
    "vowel_id": "o",
    "devanagari": "तो",
    "roman": "to",
    "mahabharata_count": 18505
  },
  {
    "id": "ta_au",
    "consonant_id": "ta",
    "vowel_id": "au",
    "devanagari": "तौ",
    "roman": "tau",
    "mahabharata_count": 3084
  },
  {
    "id": "ta_aM",
    "consonant_id": "ta",
    "vowel_id": "aM",
    "devanagari": "तं",
    "roman": "taṁ",
    "mahabharata_count": 20272
  },
  {
    "id": "ta_aH",
    "consonant_id": "ta",
    "vowel_id": "aH",
    "devanagari": "तः",
    "roman": "taḥ",
    "mahabharata_count": 21854
  },
  {
    "id": "tha_aa",
    "consonant_id": "tha",
    "vowel_id": "aa",
    "devanagari": "था",
    "roman": "thā",
    "mahabharata_count": 23729
  },
  {
    "id": "tha_i",
    "consonant_id": "tha",
    "vowel_id": "i",
    "devanagari": "थि",
    "roman": "thi",
    "mahabharata_count": 8305
  },
  {
    "id": "tha_ii",
    "consonant_id": "tha",
    "vowel_id": "ii",
    "devanagari": "थी",
    "roman": "thī",
    "mahabharata_count": 461
  },
  {
    "id": "tha_u",
    "consonant_id": "tha",
    "vowel_id": "u",
    "devanagari": "थु",
    "roman": "thu",
    "mahabharata_count": 409
  },
  {
    "id": "tha_uu",
    "consonant_id": "tha",
    "vowel_id": "uu",
    "devanagari": "थू",
    "roman": "thū",
    "mahabharata_count": 124
  },
  {
    "id": "tha_e",
    "consonant_id": "tha",
    "vowel_id": "e",
    "devanagari": "थे",
    "roman": "the",
    "mahabharata_count": 3108
  },
  {
    "id": "tha_ai",
    "consonant_id": "tha",
    "vowel_id": "ai",
    "devanagari": "थै",
    "roman": "thai",
    "mahabharata_count": 2535
  },
  {
    "id": "tha_o",
    "consonant_id": "tha",
    "vowel_id": "o",
    "devanagari": "थो",
    "roman": "tho",
    "mahabharata_count": 2159
  },
  {
    "id": "tha_au",
    "consonant_id": "tha",
    "vowel_id": "au",
    "devanagari": "थौ",
    "roman": "thau",
    "mahabharata_count": 458
  },
  {
    "id": "tha_aM",
    "consonant_id": "tha",
    "vowel_id": "aM",
    "devanagari": "थं",
    "roman": "thaṁ",
    "mahabharata_count": 5290
  },
  {
    "id": "tha_aH",
    "consonant_id": "tha",
    "vowel_id": "aH",
    "devanagari": "थः",
    "roman": "thaḥ",
    "mahabharata_count": 1375
  },
  {
    "id": "da_aa",
    "consonant_id": "da",
    "vowel_id": "aa",
    "devanagari": "दा",
    "roman": "dā",
    "mahabharata_count": 21781
  },
  {
    "id": "da_i",
    "consonant_id": "da",
    "vowel_id": "i",
    "devanagari": "दि",
    "roman": "di",
    "mahabharata_count": 13934
  },
  {
    "id": "da_ii",
    "consonant_id": "da",
    "vowel_id": "ii",
    "devanagari": "दी",
    "roman": "dī",
    "mahabharata_count": 4200
  },
  {
    "id": "da_u",
    "consonant_id": "da",
    "vowel_id": "u",
    "devanagari": "दु",
    "roman": "du",
    "mahabharata_count": 11755
  },
  {
    "id": "da_uu",
    "consonant_id": "da",
    "vowel_id": "uu",
    "devanagari": "दू",
    "roman": "dū",
    "mahabharata_count": 1155
  },
  {
    "id": "da_RRi",
    "consonant_id": "da",
    "vowel_id": "RRi",
    "devanagari": "दृ",
    "roman": "dṛ",
    "mahabharata_count": 7964
  },
  {
    "id": "da_e",
    "consonant_id": "da",
    "vowel_id": "e",
    "devanagari": "दे",
    "roman": "de",
    "mahabharata_count": 15866
  },
  {
    "id": "da_ai",
    "consonant_id": "da",
    "vowel_id": "ai",
    "devanagari": "दै",
    "roman": "dai",
    "mahabharata_count": 2050
  },
  {
    "id": "da_o",
    "consonant_id": "da",
    "vowel_id": "o",
    "devanagari": "दो",
    "roman": "do",
    "mahabharata_count": 2270
  },
  {
    "id": "da_au",
    "consonant_id": "da",
    "vowel_id": "au",
    "devanagari": "दौ",
    "roman": "dau",
    "mahabharata_count": 901
  },
  {
    "id": "da_aM",
    "consonant_id": "da",
    "vowel_id": "aM",
    "devanagari": "दं",
    "roman": "daṁ",
    "mahabharata_count": 4215
  },
  {
    "id": "da_aH",
    "consonant_id": "da",
    "vowel_id": "aH",
    "devanagari": "दः",
    "roman": "daḥ",
    "mahabharata_count": 1309
  },
  {
    "id": "dha_aa",
    "consonant_id": "dha",
    "vowel_id": "aa",
    "devanagari": "धा",
    "roman": "dhā",
    "mahabharata_count": 11894
  },
  {
    "id": "dha_i",
    "consonant_id": "dha",
    "vowel_id": "i",
    "devanagari": "धि",
    "roman": "dhi",
    "mahabharata_count": 12849
  },
  {
    "id": "dha_ii",
    "consonant_id": "dha",
    "vowel_id": "ii",
    "devanagari": "धी",
    "roman": "dhī",
    "mahabharata_count": 2146
  },
  {
    "id": "dha_u",
    "consonant_id": "dha",
    "vowel_id": "u",
    "devanagari": "धु",
    "roman": "dhu",
    "mahabharata_count": 2310
  },
  {
    "id": "dha_uu",
    "consonant_id": "dha",
    "vowel_id": "uu",
    "devanagari": "धू",
    "roman": "dhū",
    "mahabharata_count": 751
  },
  {
    "id": "dha_RRi",
    "consonant_id": "dha",
    "vowel_id": "RRi",
    "devanagari": "धृ",
    "roman": "dhṛ",
    "mahabharata_count": 2632
  },
  {
    "id": "dha_RRI",
    "consonant_id": "dha",
    "vowel_id": "RRI",
    "devanagari": "धॄ",
    "roman": "dhṝ",
    "mahabharata_count": 1
  },
  {
    "id": "dha_e",
    "consonant_id": "dha",
    "vowel_id": "e",
    "devanagari": "धे",
    "roman": "dhe",
    "mahabharata_count": 3257
  },
  {
    "id": "dha_ai",
    "consonant_id": "dha",
    "vowel_id": "ai",
    "devanagari": "धै",
    "roman": "dhai",
    "mahabharata_count": 995
  },
  {
    "id": "dha_o",
    "consonant_id": "dha",
    "vowel_id": "o",
    "devanagari": "धो",
    "roman": "dho",
    "mahabharata_count": 1831
  },
  {
    "id": "dha_au",
    "consonant_id": "dha",
    "vowel_id": "au",
    "devanagari": "धौ",
    "roman": "dhau",
    "mahabharata_count": 617
  },
  {
    "id": "dha_aM",
    "consonant_id": "dha",
    "vowel_id": "aM",
    "devanagari": "धं",
    "roman": "dhaṁ",
    "mahabharata_count": 2493
  },
  {
    "id": "dha_aH",
    "consonant_id": "dha",
    "vowel_id": "aH",
    "devanagari": "धः",
    "roman": "dhaḥ",
    "mahabharata_count": 1197
  },
  {
    "id": "na_aa",
    "consonant_id": "na",
    "vowel_id": "aa",
    "devanagari": "ना",
    "roman": "nā",
    "mahabharata_count": 47709
  },
  {
    "id": "na_i",
    "consonant_id": "na",
    "vowel_id": "i",
    "devanagari": "नि",
    "roman": "ni",
    "mahabharata_count": 37466
  },
  {
    "id": "na_ii",
    "consonant_id": "na",
    "vowel_id": "ii",
    "devanagari": "नी",
    "roman": "nī",
    "mahabharata_count": 6472
  },
  {
    "id": "na_u",
    "consonant_id": "na",
    "vowel_id": "u",
    "devanagari": "नु",
    "roman": "nu",
    "mahabharata_count": 12922
  },
  {
    "id": "na_uu",
    "consonant_id": "na",
    "vowel_id": "uu",
    "devanagari": "नू",
    "roman": "nū",
    "mahabharata_count": 553
  },
  {
    "id": "na_RRi",
    "consonant_id": "na",
    "vowel_id": "RRi",
    "devanagari": "नृ",
    "roman": "nṛ",
    "mahabharata_count": 3971
  },
  {
    "id": "na_RRI",
    "consonant_id": "na",
    "vowel_id": "RRI",
    "devanagari": "नॄ",
    "roman": "nṝ",
    "mahabharata_count": 29
  },
  {
    "id": "na_e",
    "consonant_id": "na",
    "vowel_id": "e",
    "devanagari": "ने",
    "roman": "ne",
    "mahabharata_count": 11018
  },
  {
    "id": "na_ai",
    "consonant_id": "na",
    "vowel_id": "ai",
    "devanagari": "नै",
    "roman": "nai",
    "mahabharata_count": 3613
  },
  {
    "id": "na_o",
    "consonant_id": "na",
    "vowel_id": "o",
    "devanagari": "नो",
    "roman": "no",
    "mahabharata_count": 7430
  },
  {
    "id": "na_au",
    "consonant_id": "na",
    "vowel_id": "au",
    "devanagari": "नौ",
    "roman": "nau",
    "mahabharata_count": 1193
  },
  {
    "id": "na_aM",
    "consonant_id": "na",
    "vowel_id": "aM",
    "devanagari": "नं",
    "roman": "naṁ",
    "mahabharata_count": 13018
  },
  {
    "id": "na_aH",
    "consonant_id": "na",
    "vowel_id": "aH",
    "devanagari": "नः",
    "roman": "naḥ",
    "mahabharata_count": 11489
  },
  {
    "id": "pa_aa",
    "consonant_id": "pa",
    "vowel_id": "aa",
    "devanagari": "पा",
    "roman": "pā",
    "mahabharata_count": 29743
  },
  {
    "id": "pa_i",
    "consonant_id": "pa",
    "vowel_id": "i",
    "devanagari": "पि",
    "roman": "pi",
    "mahabharata_count": 14878
  },
  {
    "id": "pa_ii",
    "consonant_id": "pa",
    "vowel_id": "ii",
    "devanagari": "पी",
    "roman": "pī",
    "mahabharata_count": 1481
  },
  {
    "id": "pa_u",
    "consonant_id": "pa",
    "vowel_id": "u",
    "devanagari": "पु",
    "roman": "pu",
    "mahabharata_count": 22817
  },
  {
    "id": "pa_uu",
    "consonant_id": "pa",
    "vowel_id": "uu",
    "devanagari": "पू",
    "roman": "pū",
    "mahabharata_count": 5460
  },
  {
    "id": "pa_RRi",
    "consonant_id": "pa",
    "vowel_id": "RRi",
    "devanagari": "पृ",
    "roman": "pṛ",
    "mahabharata_count": 4514
  },
  {
    "id": "pa_e",
    "consonant_id": "pa",
    "vowel_id": "e",
    "devanagari": "पे",
    "roman": "pe",
    "mahabharata_count": 2900
  },
  {
    "id": "pa_ai",
    "consonant_id": "pa",
    "vowel_id": "ai",
    "devanagari": "पै",
    "roman": "pai",
    "mahabharata_count": 747
  },
  {
    "id": "pa_o",
    "consonant_id": "pa",
    "vowel_id": "o",
    "devanagari": "पो",
    "roman": "po",
    "mahabharata_count": 2188
  },
  {
    "id": "pa_au",
    "consonant_id": "pa",
    "vowel_id": "au",
    "devanagari": "पौ",
    "roman": "pau",
    "mahabharata_count": 1086
  },
  {
    "id": "pa_aM",
    "consonant_id": "pa",
    "vowel_id": "aM",
    "devanagari": "पं",
    "roman": "paṁ",
    "mahabharata_count": 1724
  },
  {
    "id": "pa_aH",
    "consonant_id": "pa",
    "vowel_id": "aH",
    "devanagari": "पः",
    "roman": "paḥ",
    "mahabharata_count": 1676
  },
  {
    "id": "pha_aa",
    "consonant_id": "pha",
    "vowel_id": "aa",
    "devanagari": "फा",
    "roman": "phā",
    "mahabharata_count": 185
  },
  {
    "id": "pha_i",
    "consonant_id": "pha",
    "vowel_id": "i",
    "devanagari": "फि",
    "roman": "phi",
    "mahabharata_count": 9
  },
  {
    "id": "pha_ii",
    "consonant_id": "pha",
    "vowel_id": "ii",
    "devanagari": "फी",
    "roman": "phī",
    "mahabharata_count": 67
  },
  {
    "id": "pha_u",
    "consonant_id": "pha",
    "vowel_id": "u",
    "devanagari": "फु",
    "roman": "phu",
    "mahabharata_count": 195
  },
  {
    "id": "pha_uu",
    "consonant_id": "pha",
    "vowel_id": "uu",
    "devanagari": "फू",
    "roman": "phū",
    "mahabharata_count": 26
  },
  {
    "id": "pha_e",
    "consonant_id": "pha",
    "vowel_id": "e",
    "devanagari": "फे",
    "roman": "phe",
    "mahabharata_count": 76
  },
  {
    "id": "pha_ai",
    "consonant_id": "pha",
    "vowel_id": "ai",
    "devanagari": "फै",
    "roman": "phai",
    "mahabharata_count": 1
  },
  {
    "id": "pha_o",
    "consonant_id": "pha",
    "vowel_id": "o",
    "devanagari": "फो",
    "roman": "pho",
    "mahabharata_count": 43
  },
  {
    "id": "pha_aM",
    "consonant_id": "pha",
    "vowel_id": "aM",
    "devanagari": "फं",
    "roman": "phaṁ",
    "mahabharata_count": 2
  },
  {
    "id": "ba_aa",
    "consonant_id": "ba",
    "vowel_id": "aa",
    "devanagari": "बा",
    "roman": "bā",
    "mahabharata_count": 5644
  },
  {
    "id": "ba_i",
    "consonant_id": "ba",
    "vowel_id": "i",
    "devanagari": "बि",
    "roman": "bi",
    "mahabharata_count": 1157
  },
  {
    "id": "ba_ii",
    "consonant_id": "ba",
    "vowel_id": "ii",
    "devanagari": "बी",
    "roman": "bī",
    "mahabharata_count": 501
  },
  {
    "id": "ba_u",
    "consonant_id": "ba",
    "vowel_id": "u",
    "devanagari": "बु",
    "roman": "bu",
    "mahabharata_count": 3724
  },
  {
    "id": "ba_uu",
    "consonant_id": "ba",
    "vowel_id": "uu",
    "devanagari": "बू",
    "roman": "bū",
    "mahabharata_count": 156
  },
  {
    "id": "ba_RRi",
    "consonant_id": "ba",
    "vowel_id": "RRi",
    "devanagari": "बृ",
    "roman": "bṛ",
    "mahabharata_count": 822
  },
  {
    "id": "ba_e",
    "consonant_id": "ba",
    "vowel_id": "e",
    "devanagari": "बे",
    "roman": "be",
    "mahabharata_count": 220
  },
  {
    "id": "ba_ai",
    "consonant_id": "ba",
    "vowel_id": "ai",
    "devanagari": "बै",
    "roman": "bai",
    "mahabharata_count": 15
  },
  {
    "id": "ba_o",
    "consonant_id": "ba",
    "vowel_id": "o",
    "devanagari": "बो",
    "roman": "bo",
    "mahabharata_count": 759
  },
  {
    "id": "ba_au",
    "consonant_id": "ba",
    "vowel_id": "au",
    "devanagari": "बौ",
    "roman": "bau",
    "mahabharata_count": 4
  },
  {
    "id": "ba_aM",
    "consonant_id": "ba",
    "vowel_id": "aM",
    "devanagari": "बं",
    "roman": "baṁ",
    "mahabharata_count": 48
  },
  {
    "id": "ba_aH",
    "consonant_id": "ba",
    "vowel_id": "aH",
    "devanagari": "बः",
    "roman": "baḥ",
    "mahabharata_count": 25
  },
  {
    "id": "bha_aa",
    "consonant_id": "bha",
    "vowel_id": "aa",
    "devanagari": "भा",
    "roman": "bhā",
    "mahabharata_count": 13218
  },
  {
    "id": "bha_i",
    "consonant_id": "bha",
    "vowel_id": "i",
    "devanagari": "भि",
    "roman": "bhi",
    "mahabharata_count": 15959
  },
  {
    "id": "bha_ii",
    "consonant_id": "bha",
    "vowel_id": "ii",
    "devanagari": "भी",
    "roman": "bhī",
    "mahabharata_count": 7453
  },
  {
    "id": "bha_u",
    "consonant_id": "bha",
    "vowel_id": "u",
    "devanagari": "भु",
    "roman": "bhu",
    "mahabharata_count": 3942
  },
  {
    "id": "bha_uu",
    "consonant_id": "bha",
    "vowel_id": "uu",
    "devanagari": "भू",
    "roman": "bhū",
    "mahabharata_count": 9542
  },
  {
    "id": "bha_RRi",
    "consonant_id": "bha",
    "vowel_id": "RRi",
    "devanagari": "भृ",
    "roman": "bhṛ",
    "mahabharata_count": 2582
  },
  {
    "id": "bha_e",
    "consonant_id": "bha",
    "vowel_id": "e",
    "devanagari": "भे",
    "roman": "bhe",
    "mahabharata_count": 2077
  },
  {
    "id": "bha_ai",
    "consonant_id": "bha",
    "vowel_id": "ai",
    "devanagari": "भै",
    "roman": "bhai",
    "mahabharata_count": 615
  },
  {
    "id": "bha_o",
    "consonant_id": "bha",
    "vowel_id": "o",
    "devanagari": "भो",
    "roman": "bho",
    "mahabharata_count": 2825
  },
  {
    "id": "bha_au",
    "consonant_id": "bha",
    "vowel_id": "au",
    "devanagari": "भौ",
    "roman": "bhau",
    "mahabharata_count": 965
  },
  {
    "id": "bha_aM",
    "consonant_id": "bha",
    "vowel_id": "aM",
    "devanagari": "भं",
    "roman": "bhaṁ",
    "mahabharata_count": 670
  },
  {
    "id": "bha_aH",
    "consonant_id": "bha",
    "vowel_id": "aH",
    "devanagari": "भः",
    "roman": "bhaḥ",
    "mahabharata_count": 624
  },
  {
    "id": "ma_aa",
    "consonant_id": "ma",
    "vowel_id": "aa",
    "devanagari": "मा",
    "roman": "mā",
    "mahabharata_count": 59927
  },
  {
    "id": "ma_i",
    "consonant_id": "ma",
    "vowel_id": "i",
    "devanagari": "मि",
    "roman": "mi",
    "mahabharata_count": 22855
  },
  {
    "id": "ma_ii",
    "consonant_id": "ma",
    "vowel_id": "ii",
    "devanagari": "मी",
    "roman": "mī",
    "mahabharata_count": 2363
  },
  {
    "id": "ma_u",
    "consonant_id": "ma",
    "vowel_id": "u",
    "devanagari": "मु",
    "roman": "mu",
    "mahabharata_count": 18917
  },
  {
    "id": "ma_uu",
    "consonant_id": "ma",
    "vowel_id": "uu",
    "devanagari": "मू",
    "roman": "mū",
    "mahabharata_count": 2733
  },
  {
    "id": "ma_RRi",
    "consonant_id": "ma",
    "vowel_id": "RRi",
    "devanagari": "मृ",
    "roman": "mṛ",
    "mahabharata_count": 5614
  },
  {
    "id": "ma_e",
    "consonant_id": "ma",
    "vowel_id": "e",
    "devanagari": "मे",
    "roman": "me",
    "mahabharata_count": 19139
  },
  {
    "id": "ma_ai",
    "consonant_id": "ma",
    "vowel_id": "ai",
    "devanagari": "मै",
    "roman": "mai",
    "mahabharata_count": 1907
  },
  {
    "id": "ma_o",
    "consonant_id": "ma",
    "vowel_id": "o",
    "devanagari": "मो",
    "roman": "mo",
    "mahabharata_count": 6267
  },
  {
    "id": "ma_au",
    "consonant_id": "ma",
    "vowel_id": "au",
    "devanagari": "मौ",
    "roman": "mau",
    "mahabharata_count": 1136
  },
  {
    "id": "ma_aM",
    "consonant_id": "ma",
    "vowel_id": "aM",
    "devanagari": "मं",
    "roman": "maṁ",
    "mahabharata_count": 4902
  },
  {
    "id": "ma_aH",
    "consonant_id": "ma",
    "vowel_id": "aH",
    "devanagari": "मः",
    "roman": "maḥ",
    "mahabharata_count": 4119
  },
  {
    "id": "ya_aa",
    "consonant_id": "ya",
    "vowel_id": "aa",
    "devanagari": "या",
    "roman": "yā",
    "mahabharata_count": 65779
  },
  {
    "id": "ya_i",
    "consonant_id": "ya",
    "vowel_id": "i",
    "devanagari": "यि",
    "roman": "yi",
    "mahabharata_count": 3892
  },
  {
    "id": "ya_ii",
    "consonant_id": "ya",
    "vowel_id": "ii",
    "devanagari": "यी",
    "roman": "yī",
    "mahabharata_count": 364
  },
  {
    "id": "ya_u",
    "consonant_id": "ya",
    "vowel_id": "u",
    "devanagari": "यु",
    "roman": "yu",
    "mahabharata_count": 22969
  },
  {
    "id": "ya_uu",
    "consonant_id": "ya",
    "vowel_id": "uu",
    "devanagari": "यू",
    "roman": "yū",
    "mahabharata_count": 1397
  },
  {
    "id": "ya_RRi",
    "consonant_id": "ya",
    "vowel_id": "RRi",
    "devanagari": "यृ",
    "roman": "yṛ",
    "mahabharata_count": 59
  },
  {
    "id": "ya_e",
    "consonant_id": "ya",
    "vowel_id": "e",
    "devanagari": "ये",
    "roman": "ye",
    "mahabharata_count": 21363
  },
  {
    "id": "ya_ai",
    "consonant_id": "ya",
    "vowel_id": "ai",
    "devanagari": "यै",
    "roman": "yai",
    "mahabharata_count": 3173
  },
  {
    "id": "ya_o",
    "consonant_id": "ya",
    "vowel_id": "o",
    "devanagari": "यो",
    "roman": "yo",
    "mahabharata_count": 20070
  },
  {
    "id": "ya_au",
    "consonant_id": "ya",
    "vowel_id": "au",
    "devanagari": "यौ",
    "roman": "yau",
    "mahabharata_count": 1815
  },
  {
    "id": "ya_aM",
    "consonant_id": "ya",
    "vowel_id": "aM",
    "devanagari": "यं",
    "roman": "yaṁ",
    "mahabharata_count": 19789
  },
  {
    "id": "ya_aH",
    "consonant_id": "ya",
    "vowel_id": "aH",
    "devanagari": "यः",
    "roman": "yaḥ",
    "mahabharata_count": 8881
  },
  {
    "id": "ra_aa",
    "consonant_id": "ra",
    "vowel_id": "aa",
    "devanagari": "रा",
    "roman": "rā",
    "mahabharata_count": 75888
  },
  {
    "id": "ra_i",
    "consonant_id": "ra",
    "vowel_id": "i",
    "devanagari": "रि",
    "roman": "ri",
    "mahabharata_count": 25214
  },
  {
    "id": "ra_ii",
    "consonant_id": "ra",
    "vowel_id": "ii",
    "devanagari": "री",
    "roman": "rī",
    "mahabharata_count": 9011
  },
  {
    "id": "ra_u",
    "consonant_id": "ra",
    "vowel_id": "u",
    "devanagari": "रु",
    "roman": "ru",
    "mahabharata_count": 23607
  },
  {
    "id": "ra_uu",
    "consonant_id": "ra",
    "vowel_id": "uu",
    "devanagari": "रू",
    "roman": "rū",
    "mahabharata_count": 6371
  },
  {
    "id": "ra_RRi",
    "consonant_id": "ra",
    "vowel_id": "RRi",
    "devanagari": "रृ",
    "roman": "rṛ",
    "mahabharata_count": 111
  },
  {
    "id": "ra_e",
    "consonant_id": "ra",
    "vowel_id": "e",
    "devanagari": "रे",
    "roman": "re",
    "mahabharata_count": 18873
  },
  {
    "id": "ra_ai",
    "consonant_id": "ra",
    "vowel_id": "ai",
    "devanagari": "रै",
    "roman": "rai",
    "mahabharata_count": 5540
  },
  {
    "id": "ra_o",
    "consonant_id": "ra",
    "vowel_id": "o",
    "devanagari": "रो",
    "roman": "ro",
    "mahabharata_count": 16341
  },
  {
    "id": "ra_au",
    "consonant_id": "ra",
    "vowel_id": "au",
    "devanagari": "रौ",
    "roman": "rau",
    "mahabharata_count": 3032
  },
  {
    "id": "ra_aM",
    "consonant_id": "ra",
    "vowel_id": "aM",
    "devanagari": "रं",
    "roman": "raṁ",
    "mahabharata_count": 13911
  },
  {
    "id": "ra_aH",
    "consonant_id": "ra",
    "vowel_id": "aH",
    "devanagari": "रः",
    "roman": "raḥ",
    "mahabharata_count": 7172
  },
  {
    "id": "la_aa",
    "consonant_id": "la",
    "vowel_id": "aa",
    "devanagari": "ला",
    "roman": "lā",
    "mahabharata_count": 8237
  },
  {
    "id": "la_i",
    "consonant_id": "la",
    "vowel_id": "i",
    "devanagari": "लि",
    "roman": "li",
    "mahabharata_count": 3787
  },
  {
    "id": "la_ii",
    "consonant_id": "la",
    "vowel_id": "ii",
    "devanagari": "ली",
    "roman": "lī",
    "mahabharata_count": 1553
  },
  {
    "id": "la_u",
    "consonant_id": "la",
    "vowel_id": "u",
    "devanagari": "लु",
    "roman": "lu",
    "mahabharata_count": 966
  },
  {
    "id": "la_uu",
    "consonant_id": "la",
    "vowel_id": "uu",
    "devanagari": "लू",
    "roman": "lū",
    "mahabharata_count": 186
  },
  {
    "id": "la_RRi",
    "consonant_id": "la",
    "vowel_id": "RRi",
    "devanagari": "लृ",
    "roman": "lṛ",
    "mahabharata_count": 2
  },
  {
    "id": "la_e",
    "consonant_id": "la",
    "vowel_id": "e",
    "devanagari": "ले",
    "roman": "le",
    "mahabharata_count": 4865
  },
  {
    "id": "la_ai",
    "consonant_id": "la",
    "vowel_id": "ai",
    "devanagari": "लै",
    "roman": "lai",
    "mahabharata_count": 907
  },
  {
    "id": "la_o",
    "consonant_id": "la",
    "vowel_id": "o",
    "devanagari": "लो",
    "roman": "lo",
    "mahabharata_count": 9536
  },
  {
    "id": "la_au",
    "consonant_id": "la",
    "vowel_id": "au",
    "devanagari": "लौ",
    "roman": "lau",
    "mahabharata_count": 339
  },
  {
    "id": "la_aM",
    "consonant_id": "la",
    "vowel_id": "aM",
    "devanagari": "लं",
    "roman": "laṁ",
    "mahabharata_count": 4598
  },
  {
    "id": "la_aH",
    "consonant_id": "la",
    "vowel_id": "aH",
    "devanagari": "लः",
    "roman": "laḥ",
    "mahabharata_count": 1820
  },
  {
    "id": "va_aa",
    "consonant_id": "va",
    "vowel_id": "aa",
    "devanagari": "वा",
    "roman": "vā",
    "mahabharata_count": 74363
  },
  {
    "id": "va_i",
    "consonant_id": "va",
    "vowel_id": "i",
    "devanagari": "वि",
    "roman": "vi",
    "mahabharata_count": 56882
  },
  {
    "id": "va_ii",
    "consonant_id": "va",
    "vowel_id": "ii",
    "devanagari": "वी",
    "roman": "vī",
    "mahabharata_count": 11152
  },
  {
    "id": "va_u",
    "consonant_id": "va",
    "vowel_id": "u",
    "devanagari": "वु",
    "roman": "vu",
    "mahabharata_count": 824
  },
  {
    "id": "va_uu",
    "consonant_id": "va",
    "vowel_id": "uu",
    "devanagari": "वू",
    "roman": "vū",
    "mahabharata_count": 26
  },
  {
    "id": "va_RRi",
    "consonant_id": "va",
    "vowel_id": "RRi",
    "devanagari": "वृ",
    "roman": "vṛ",
    "mahabharata_count": 8538
  },
  {
    "id": "va_e",
    "consonant_id": "va",
    "vowel_id": "e",
    "devanagari": "वे",
    "roman": "ve",
    "mahabharata_count": 19031
  },
  {
    "id": "va_ai",
    "consonant_id": "va",
    "vowel_id": "ai",
    "devanagari": "वै",
    "roman": "vai",
    "mahabharata_count": 11344
  },
  {
    "id": "va_o",
    "consonant_id": "va",
    "vowel_id": "o",
    "devanagari": "वो",
    "roman": "vo",
    "mahabharata_count": 4089
  },
  {
    "id": "va_au",
    "consonant_id": "va",
    "vowel_id": "au",
    "devanagari": "वौ",
    "roman": "vau",
    "mahabharata_count": 594
  },
  {
    "id": "va_aM",
    "consonant_id": "va",
    "vowel_id": "aM",
    "devanagari": "वं",
    "roman": "vaṁ",
    "mahabharata_count": 13361
  },
  {
    "id": "va_aH",
    "consonant_id": "va",
    "vowel_id": "aH",
    "devanagari": "वः",
    "roman": "vaḥ",
    "mahabharata_count": 3951
  },
  {
    "id": "sha_aa",
    "consonant_id": "sha",
    "vowel_id": "aa",
    "devanagari": "शा",
    "roman": "śā",
    "mahabharata_count": 9855
  },
  {
    "id": "sha_i",
    "consonant_id": "sha",
    "vowel_id": "i",
    "devanagari": "शि",
    "roman": "śi",
    "mahabharata_count": 7212
  },
  {
    "id": "sha_ii",
    "consonant_id": "sha",
    "vowel_id": "ii",
    "devanagari": "शी",
    "roman": "śī",
    "mahabharata_count": 2449
  },
  {
    "id": "sha_u",
    "consonant_id": "sha",
    "vowel_id": "u",
    "devanagari": "शु",
    "roman": "śu",
    "mahabharata_count": 6282
  },
  {
    "id": "sha_uu",
    "consonant_id": "sha",
    "vowel_id": "uu",
    "devanagari": "शू",
    "roman": "śū",
    "mahabharata_count": 2200
  },
  {
    "id": "sha_RRi",
    "consonant_id": "sha",
    "vowel_id": "RRi",
    "devanagari": "शृ",
    "roman": "śṛ",
    "mahabharata_count": 1695
  },
  {
    "id": "sha_e",
    "consonant_id": "sha",
    "vowel_id": "e",
    "devanagari": "शे",
    "roman": "śe",
    "mahabharata_count": 3262
  },
  {
    "id": "sha_ai",
    "consonant_id": "sha",
    "vowel_id": "ai",
    "devanagari": "शै",
    "roman": "śai",
    "mahabharata_count": 1046
  },
  {
    "id": "sha_o",
    "consonant_id": "sha",
    "vowel_id": "o",
    "devanagari": "शो",
    "roman": "śo",
    "mahabharata_count": 4154
  },
  {
    "id": "sha_au",
    "consonant_id": "sha",
    "vowel_id": "au",
    "devanagari": "शौ",
    "roman": "śau",
    "mahabharata_count": 583
  },
  {
    "id": "sha_aM",
    "consonant_id": "sha",
    "vowel_id": "aM",
    "devanagari": "शं",
    "roman": "śaṁ",
    "mahabharata_count": 4966
  },
  {
    "id": "sha_aH",
    "consonant_id": "sha",
    "vowel_id": "aH",
    "devanagari": "शः",
    "roman": "śaḥ",
    "mahabharata_count": 2623
  },
  {
    "id": "Sha_aa",
    "consonant_id": "Sha",
    "vowel_id": "aa",
    "devanagari": "षा",
    "roman": "ṣā",
    "mahabharata_count": 7766
  },
  {
    "id": "Sha_i",
    "consonant_id": "Sha",
    "vowel_id": "i",
    "devanagari": "षि",
    "roman": "ṣi",
    "mahabharata_count": 4729
  },
  {
    "id": "Sha_ii",
    "consonant_id": "Sha",
    "vowel_id": "ii",
    "devanagari": "षी",
    "roman": "ṣī",
    "mahabharata_count": 1214
  },
  {
    "id": "Sha_u",
    "consonant_id": "Sha",
    "vowel_id": "u",
    "devanagari": "षु",
    "roman": "ṣu",
    "mahabharata_count": 7314
  },
  {
    "id": "Sha_uu",
    "consonant_id": "Sha",
    "vowel_id": "uu",
    "devanagari": "षू",
    "roman": "ṣū",
    "mahabharata_count": 178
  },
  {
    "id": "Sha_e",
    "consonant_id": "Sha",
    "vowel_id": "e",
    "devanagari": "षे",
    "roman": "ṣe",
    "mahabharata_count": 2543
  },
  {
    "id": "Sha_ai",
    "consonant_id": "Sha",
    "vowel_id": "ai",
    "devanagari": "षै",
    "roman": "ṣai",
    "mahabharata_count": 429
  },
  {
    "id": "Sha_o",
    "consonant_id": "Sha",
    "vowel_id": "o",
    "devanagari": "षो",
    "roman": "ṣo",
    "mahabharata_count": 1359
  },
  {
    "id": "Sha_au",
    "consonant_id": "Sha",
    "vowel_id": "au",
    "devanagari": "षौ",
    "roman": "ṣau",
    "mahabharata_count": 80
  },
  {
    "id": "Sha_aM",
    "consonant_id": "Sha",
    "vowel_id": "aM",
    "devanagari": "षं",
    "roman": "ṣaṁ",
    "mahabharata_count": 1447
  },
  {
    "id": "Sha_aH",
    "consonant_id": "Sha",
    "vowel_id": "aH",
    "devanagari": "षः",
    "roman": "ṣaḥ",
    "mahabharata_count": 924
  },
  {
    "id": "sa_aa",
    "consonant_id": "sa",
    "vowel_id": "aa",
    "devanagari": "सा",
    "roman": "sā",
    "mahabharata_count": 19329
  },
  {
    "id": "sa_i",
    "consonant_id": "sa",
    "vowel_id": "i",
    "devanagari": "सि",
    "roman": "si",
    "mahabharata_count": 9465
  },
  {
    "id": "sa_ii",
    "consonant_id": "sa",
    "vowel_id": "ii",
    "devanagari": "सी",
    "roman": "sī",
    "mahabharata_count": 2644
  },
  {
    "id": "sa_u",
    "consonant_id": "sa",
    "vowel_id": "u",
    "devanagari": "सु",
    "roman": "su",
    "mahabharata_count": 18476
  },
  {
    "id": "sa_uu",
    "consonant_id": "sa",
    "vowel_id": "uu",
    "devanagari": "सू",
    "roman": "sū",
    "mahabharata_count": 3955
  },
  {
    "id": "sa_RRi",
    "consonant_id": "sa",
    "vowel_id": "RRi",
    "devanagari": "सृ",
    "roman": "sṛ",
    "mahabharata_count": 2479
  },
  {
    "id": "sa_RRI",
    "consonant_id": "sa",
    "vowel_id": "RRI",
    "devanagari": "सॄ",
    "roman": "sṝ",
    "mahabharata_count": 2
  },
  {
    "id": "sa_e",
    "consonant_id": "sa",
    "vowel_id": "e",
    "devanagari": "से",
    "roman": "se",
    "mahabharata_count": 6767
  },
  {
    "id": "sa_ai",
    "consonant_id": "sa",
    "vowel_id": "ai",
    "devanagari": "सै",
    "roman": "sai",
    "mahabharata_count": 2315
  },
  {
    "id": "sa_o",
    "consonant_id": "sa",
    "vowel_id": "o",
    "devanagari": "सो",
    "roman": "so",
    "mahabharata_count": 3977
  },
  {
    "id": "sa_au",
    "consonant_id": "sa",
    "vowel_id": "au",
    "devanagari": "सौ",
    "roman": "sau",
    "mahabharata_count": 2122
  },
  {
    "id": "sa_aM",
    "consonant_id": "sa",
    "vowel_id": "aM",
    "devanagari": "सं",
    "roman": "saṁ",
    "mahabharata_count": 24111
  },
  {
    "id": "sa_aH",
    "consonant_id": "sa",
    "vowel_id": "aH",
    "devanagari": "सः",
    "roman": "saḥ",
    "mahabharata_count": 2216
  },
  {
    "id": "ha_aa",
    "consonant_id": "ha",
    "vowel_id": "aa",
    "devanagari": "हा",
    "roman": "hā",
    "mahabharata_count": 23565
  },
  {
    "id": "ha_i",
    "consonant_id": "ha",
    "vowel_id": "i",
    "devanagari": "हि",
    "roman": "hi",
    "mahabharata_count": 14024
  },
  {
    "id": "ha_ii",
    "consonant_id": "ha",
    "vowel_id": "ii",
    "devanagari": "ही",
    "roman": "hī",
    "mahabharata_count": 3042
  },
  {
    "id": "ha_u",
    "consonant_id": "ha",
    "vowel_id": "u",
    "devanagari": "हु",
    "roman": "hu",
    "mahabharata_count": 5619
  },
  {
    "id": "ha_uu",
    "consonant_id": "ha",
    "vowel_id": "uu",
    "devanagari": "हू",
    "roman": "hū",
    "mahabharata_count": 1351
  },
  {
    "id": "ha_RRi",
    "consonant_id": "ha",
    "vowel_id": "RRi",
    "devanagari": "हृ",
    "roman": "hṛ",
    "mahabharata_count": 3379
  },
  {
    "id": "ha_e",
    "consonant_id": "ha",
    "vowel_id": "e",
    "devanagari": "हे",
    "roman": "he",
    "mahabharata_count": 4208
  },
  {
    "id": "ha_ai",
    "consonant_id": "ha",
    "vowel_id": "ai",
    "devanagari": "है",
    "roman": "hai",
    "mahabharata_count": 554
  },
  {
    "id": "ha_o",
    "consonant_id": "ha",
    "vowel_id": "o",
    "devanagari": "हो",
    "roman": "ho",
    "mahabharata_count": 2359
  },
  {
    "id": "ha_au",
    "consonant_id": "ha",
    "vowel_id": "au",
    "devanagari": "हौ",
    "roman": "hau",
    "mahabharata_count": 211
  },
  {
    "id": "ha_aM",
    "consonant_id": "ha",
    "vowel_id": "aM",
    "devanagari": "हं",
    "roman": "haṁ",
    "mahabharata_count": 5086
  },
  {
    "id": "ha_aH",
    "consonant_id": "ha",
    "vowel_id": "aH",
    "devanagari": "हः",
    "roman": "haḥ",
    "mahabharata_count": 973
  },
  {
    "id": "kSha_aa",
    "consonant_id": "kSha",
    "vowel_id": "aa",
    "devanagari": "क्षा",
    "roman": "kṣā",
    "mahabharata_count": 1809
  },
  {
    "id": "kSha_i",
    "consonant_id": "kSha",
    "vowel_id": "i",
    "devanagari": "क्षि",
    "roman": "kṣi",
    "mahabharata_count": 4375
  },
  {
    "id": "kSha_ii",
    "consonant_id": "kSha",
    "vowel_id": "ii",
    "devanagari": "क्षी",
    "roman": "kṣī",
    "mahabharata_count": 696
  },
  {
    "id": "kSha_u",
    "consonant_id": "kSha",
    "vowel_id": "u",
    "devanagari": "क्षु",
    "roman": "kṣu",
    "mahabharata_count": 1519
  },
  {
    "id": "kSha_uu",
    "consonant_id": "kSha",
    "vowel_id": "uu",
    "devanagari": "क्षू",
    "roman": "kṣū",
    "mahabharata_count": 43
  },
  {
    "id": "kSha_e",
    "consonant_id": "kSha",
    "vowel_id": "e",
    "devanagari": "क्षे",
    "roman": "kṣe",
    "mahabharata_count": 1707
  },
  {
    "id": "kSha_ai",
    "consonant_id": "kSha",
    "vowel_id": "ai",
    "devanagari": "क्षै",
    "roman": "kṣai",
    "mahabharata_count": 133
  },
  {
    "id": "kSha_o",
    "consonant_id": "kSha",
    "vowel_id": "o",
    "devanagari": "क्षो",
    "roman": "kṣo",
    "mahabharata_count": 623
  },
  {
    "id": "kSha_au",
    "consonant_id": "kSha",
    "vowel_id": "au",
    "devanagari": "क्षौ",
    "roman": "kṣau",
    "mahabharata_count": 227
  },
  {
    "id": "kSha_aM",
    "consonant_id": "kSha",
    "vowel_id": "aM",
    "devanagari": "क्षं",
    "roman": "kṣaṁ",
    "mahabharata_count": 625
  },
  {
    "id": "kSha_aH",
    "consonant_id": "kSha",
    "vowel_id": "aH",
    "devanagari": "क्षः",
    "roman": "kṣaḥ",
    "mahabharata_count": 299
  },
  {
    "id": "jJNa_aa",
    "consonant_id": "jJNa",
    "vowel_id": "aa",
    "devanagari": "ज्ञा",
    "roman": "jñā",
    "mahabharata_count": 5500
  },
  {
    "id": "jJNa_i",
    "consonant_id": "jJNa",
    "vowel_id": "i",
    "devanagari": "ज्ञि",
    "roman": "jñi",
    "mahabharata_count": 231
  },
  {
    "id": "jJNa_ii",
    "consonant_id": "jJNa",
    "vowel_id": "ii",
    "devanagari": "ज्ञी",
    "roman": "jñī",
    "mahabharata_count": 14
  },
  {
    "id": "jJNa_u",
    "consonant_id": "jJNa",
    "vowel_id": "u",
    "devanagari": "ज्ञु",
    "roman": "jñu",
    "mahabharata_count": 18
  },
  {
    "id": "jJNa_e",
    "consonant_id": "jJNa",
    "vowel_id": "e",
    "devanagari": "ज्ञे",
    "roman": "jñe",
    "mahabharata_count": 1013
  },
  {
    "id": "jJNa_ai",
    "consonant_id": "jJNa",
    "vowel_id": "ai",
    "devanagari": "ज्ञै",
    "roman": "jñai",
    "mahabharata_count": 239
  },
  {
    "id": "jJNa_o",
    "consonant_id": "jJNa",
    "vowel_id": "o",
    "devanagari": "ज्ञो",
    "roman": "jño",
    "mahabharata_count": 785
  },
  {
    "id": "jJNa_au",
    "consonant_id": "jJNa",
    "vowel_id": "au",
    "devanagari": "ज्ञौ",
    "roman": "jñau",
    "mahabharata_count": 22
  },
  {
    "id": "jJNa_aM",
    "consonant_id": "jJNa",
    "vowel_id": "aM",
    "devanagari": "ज्ञं",
    "roman": "jñaṁ",
    "mahabharata_count": 306
  },
  {
    "id": "jJNa_aH",
    "consonant_id": "jJNa",
    "vowel_id": "aH",
    "devanagari": "ज्ञः",
    "roman": "jñaḥ",
    "mahabharata_count": 721
  }
]